collective/gridlisting/__init__.py
collective/gridlisting/configure.zcml
collective/gridlisting/controlpanel.py
collective/gridlisting/interfaces.py
collective/gridlisting/permissions.zcml
collective/gridlisting/setuphandlers.py
collective/gridlisting/testing.py
collective/gridlisting/upgrades.zcml
collective/gridlisting/vocabularies.py
collective/gridlisting/behaviors/__init__.py
collective/gridlisting/behaviors/configure.zcml
collective/gridlisting/behaviors/grid_listing.py
collective/gridlisting/browser/__init__.py
collective/gridlisting/browser/configure.zcml
collective/gridlisting/browser/grid_listing.pt
collective/gridlisting/browser/views.py
collective/gridlisting/browser/static/gridlisting-remote.min.js
collective/gridlisting/browser/static/gridlisting-remote.min.js.map
collective/gridlisting/browser/static/gridlisting.min.js
collective/gridlisting/browser/static/gridlisting.min.js.map
collective/gridlisting/browser/static/chunks/46.a617f8b7c24e247c3f5b.min.js
collective/gridlisting/browser/static/chunks/46.a617f8b7c24e247c3f5b.min.js.map
collective/gridlisting/browser/static/chunks/518.4dc5d9da15660cb573a5.min.js
collective/gridlisting/browser/static/chunks/518.4dc5d9da15660cb573a5.min.js.map
collective/gridlisting/browser/static/chunks/692.950c8366cf000fa3c426.min.js
collective/gridlisting/browser/static/chunks/692.950c8366cf000fa3c426.min.js.map
collective/gridlisting/browser/static/chunks/812.709a7f918530cc5e35f2.min.js
collective/gridlisting/browser/static/chunks/812.709a7f918530cc5e35f2.min.js.map
collective/gridlisting/browser/static/chunks/943.1aa83c97353d21b0a6fa.min.js
collective/gridlisting/browser/static/chunks/943.1aa83c97353d21b0a6fa.min.js.map
collective/gridlisting/browser/static/chunks/994.c2e768907c63ed8a0076.min.js
collective/gridlisting/browser/static/chunks/994.c2e768907c63ed8a0076.min.js.map
collective/gridlisting/locales/README.rst
collective/gridlisting/locales/__init__.py
collective/gridlisting/locales/collective.gridlisting.pot
collective_gridlisting-2.0.0.dist-info/licenses/LICENSE.GPL
collective_gridlisting-2.0.0.dist-info/licenses/LICENSE.rst
collective_gridlisting-2.0.0.dist-info/METADATA
collective_gridlisting-2.0.0.dist-info/WHEEL
collective_gridlisting-2.0.0.dist-info/entry_points.txt
collective_gridlisting-2.0.0.dist-info/top_level.txt
collective_gridlisting-2.0.0.dist-info/RECORD
