Metadata-Version: 2.4
Name: collective.gridlisting
Version: 2.0.0
Summary: Behavior for Folder and Collection to manipulate various appearance settings using Bootstrap (column layout) and patternslib (masonry, inject)
Home-page: https://github.com/collective/collective.gridlisting
Author: Peter Mathis
Author-email: peter.mathis@kombinat.at
License: GPL version 2
Project-URL: PyPI, https://pypi.org/project/collective.gridlisting/
Project-URL: Source, https://github.com/collective/collective.gridlisting
Project-URL: Tracker, https://github.com/collective/collective.gridlisting/issues
Keywords: Python Plone CMS Addon folder layout masonry column grid
Classifier: Development Status :: 5 - Production/Stable
Classifier: Environment :: Web Environment
Classifier: Framework :: Plone
Classifier: Framework :: Plone :: Addon
Classifier: Framework :: Plone :: 6.1
Classifier: Framework :: Plone :: 6.2
Classifier: Programming Language :: Python
Classifier: Programming Language :: Python :: 3.10
Classifier: Programming Language :: Python :: 3.11
Classifier: Programming Language :: Python :: 3.12
Classifier: Programming Language :: Python :: 3.13
Classifier: Operating System :: OS Independent
Classifier: License :: OSI Approved :: GNU General Public License v2 (GPLv2)
Requires-Python: >=3.10
License-File: LICENSE.GPL
License-File: LICENSE.rst
Requires-Dist: setuptools
Requires-Dist: plone.api>=1.8.4
Requires-Dist: plone.app.dexterity
Provides-Extra: test
Requires-Dist: plone.restapi; extra == "test"
Requires-Dist: plone.app.testing; extra == "test"
Requires-Dist: plone.testing>=5.0.0; extra == "test"
Requires-Dist: plone.app.contenttypes; extra == "test"
Requires-Dist: plone.app.robotframework[debug]; extra == "test"
Dynamic: author
Dynamic: author-email
Dynamic: classifier
Dynamic: description
Dynamic: home-page
Dynamic: keywords
Dynamic: license
Dynamic: license-file
Dynamic: project-url
Dynamic: provides-extra
Dynamic: requires-dist
Dynamic: requires-python
Dynamic: summary
